fair_meeting_planner-0.1.0.dist-info/licenses/LICENSE
fairmeeting/__init__.py
fairmeeting/cli.py
fairmeeting/cost.py
fairmeeting/export.py
fairmeeting/schemas.py
fairmeeting/solver.py
fairmeeting/timezones.py
fair_meeting_planner-0.1.0.dist-info/METADATA
fair_meeting_planner-0.1.0.dist-info/WHEEL
fair_meeting_planner-0.1.0.dist-info/entry_points.txt
fair_meeting_planner-0.1.0.dist-info/top_level.txt
fair_meeting_planner-0.1.0.dist-info/RECORD
