Metadata-Version: 2.4
Name: fair-meeting-planner
Version: 0.1.0
Summary: A library that finds fair, repeatable meeting times for globally distributed teams.
Author-email: Andrew Babu Augustine <andrewbaugustine@gmail.com>
Project-URL: Homepage, https://github.com/andrewbabu/fairmeeting
Project-URL: Bug Tracker, https://github.com/andrewbabu/fairmeeting/issues
Classifier: Programming Language :: Python :: 3
Classifier: License :: OSI Approved :: MIT License
Classifier: Operating System :: OS Independent
Requires-Python: >=3.9
License-File: LICENSE
Requires-Dist: pydantic
Requires-Dist: pytz
Requires-Dist: pandas
Requires-Dist: numpy
Requires-Dist: pulp
Requires-Dist: ics
Requires-Dist: rich
Requires-Dist: pyyaml
Provides-Extra: dev
Requires-Dist: pytest; extra == "dev"
Requires-Dist: ruff; extra == "dev"
Dynamic: license-file
